colorama/__init__.py
colorama/ansi.py
colorama/ansitowin32.py
colorama/initialise.py
colorama/win32.py
colorama/winterm.py
lgr/__init__.py
lgr/logger.py
Logger3-0.1.1.dist-info/LICENSE
Logger3-0.1.1.dist-info/METADATA
Logger3-0.1.1.dist-info/WHEEL
Logger3-0.1.1.dist-info/top_level.txt
Logger3-0.1.1.dist-info/RECORD
