Metadata-Version: 2.1
Name: Logger3
Version: 0.1.1
Summary: Loging Easy
Home-page: UNKNOWN
Author: Harsha Adddanki
Author-email: harsha7addanki@gmail.com
License: UNKNOWN
Platform: UNKNOWN
Classifier: Programming Language :: Python :: 3
Classifier: License :: OSI Approved :: MIT License
Classifier: Operating System :: OS Independent
Requires-Python: >=3.8.5
